README.md
setup.py
easysmart/__init__.py
easysmart/func.py
easysmart/manager.py
easysmart/utils.py
easysmart.egg-info/PKG-INFO
easysmart.egg-info/SOURCES.txt
easysmart.egg-info/dependency_links.txt
easysmart.egg-info/requires.txt
easysmart.egg-info/top_level.txt
easysmart/automatic/__init__.py
easysmart/automatic/base_service.py
easysmart/device/__init__.py
easysmart/device/base_device.py
easysmart/device/device_define.py
easysmart/device/virtual_device/__init__.py
easysmart/device/virtual_device/virtual_base_device.py
easysmart/mdns/__init__.py
easysmart/mdns/mdns.py
easysmart/mdns/mdns_async.py
easysmart/mqtt_server/__init__.py
easysmart/mqtt_server/mqtt_server.py
easysmart/mqtt_server/port_in_use_check.py
easysmart/web/__init__.py
easysmart/web/webmain.py