Metadata-Version: 2.1
Name: easysmart
Version: 20250201143426
Summary: 简单智能官方实现
Home-page: http://easysmart.top
Author: jiandanzhineng
Author-email: jiandanzhineng@outlook.com
Classifier: Programming Language :: Python :: 3
Classifier: License :: OSI Approved :: MIT License
Classifier: Operating System :: Microsoft :: Windows
